injecty_config_marshy/__init__.py
marshy/__init__.py
marshy/errors.py
marshy/marshy_context.py
marshy/types.py
marshy/utils.py
marshy/factory/__init__.py
marshy/factory/dataclass_marshaller_factory.py
marshy/factory/enum_marshaller_factory.py
marshy/factory/factory_marshaller_factory.py
marshy/factory/impl_marshaller_factory.py
marshy/factory/list_marshaller_factory.py
marshy/factory/marshaller_factory_abc.py
marshy/factory/optional_marshaller_factory.py
marshy/factory/tuple_marshaller_factory.py
marshy/factory/union_marshaller_factory.py
marshy/marshaller/__init__.py
marshy/marshaller/as_str_marshaller.py
marshy/marshaller/bool_marshaller.py
marshy/marshaller/datetime_marshaller.py
marshy/marshaller/deferred_marshaller.py
marshy/marshaller/enum_marshaller.py
marshy/marshaller/iterable_marshaller.py
marshy/marshaller/json_str_marshaller.py
marshy/marshaller/marshaller_abc.py
marshy/marshaller/no_op_marshaller.py
marshy/marshaller/obj_marshaller.py
marshy/marshaller/optional_marshaller.py
marshy/marshaller/primitive_marshaller.py
marshy/marshaller/property_marshaller.py
marshy/marshaller/tuple_marshaller.py
marshy/marshaller/type_marshaller.py
marshy/marshaller/union_marshaller.py
marshy-6.0.0.dist-info/METADATA
marshy-6.0.0.dist-info/WHEEL
marshy-6.0.0.dist-info/licenses/LICENSE
marshy-6.0.0.dist-info/RECORD
