Metadata-Version: 2.4
Name: marshy
Version: 6.0.0
Summary: A convention over configuration approach to object marshalling.
Project-URL: Repository, https://github.com/tofarr/marshy
Author-email: Tim O'Farrell <tofarr@gmail.com>
License: MIT
License-File: LICENSE
Classifier: License :: OSI Approved :: MIT License
Classifier: Operating System :: OS Independent
Classifier: Programming Language :: Python :: 3
Requires-Python: >=3.10
Requires-Dist: injecty~=0.0
Requires-Dist: typing-inspect~=0.7
Provides-Extra: dev
Requires-Dist: black>=23.3; extra == 'dev'
Requires-Dist: marshmallow-dataclass>=8.5; extra == 'dev'
Requires-Dist: pylint>=3.0; extra == 'dev'
Requires-Dist: pytest-cov>=4.0; extra == 'dev'
Requires-Dist: pytest-xdist>=3.2; extra == 'dev'
Requires-Dist: pytest>=7.2; extra == 'dev'
